d_latch.v
module d_latch(CLK, D, Q, Qbar);
	input CLK, D;
	output Q, Qbar;
	wire not_d, and_0, and_1;

	not(not_d, D);
	and(and_0, CLK, not_d);
	and(and_1, CLK, D);
	nor(Q, and_0, Qbar);
	nor(Qbar, and_1, Q);
endmodule

d_flip_flop.v
module d_flip_flop(CLK, D, Q, Qbar);
	input CLK, D;
	output Q, Qbar;
	wire not_clk, q_0, qbar_0;

	not(not_clk, CLK);
	d_latch DL_0(CLK, 			D, 		q_0, 	qbar_0);
	d_latch DL_1(not_clk, 	q_0, 	Q, 		Qbar);
endmodule

d_flip_flop_TB.v
`timescale 1ns/100ps

module d_flip_flop_TB();
  reg CLK, D;
	wire Q, Qbar;
  
  d_flip_flop DL(
    .CLK(CLK),
    .D(D),
    .Q(Q),
    .Qbar(Qbar)
    );

	always #50 CLK = ~CLK;
  
  initial begin 
    $dumpfile("test.vcd"); 
    $dumpvars(1,d_flip_flop_TB);
		D=0;
		CLK=0;
    #125  D=1;
    #150  D=0;
    #150  D=1;
    #100  $finish;
  end
endmodule

test.vcd
$date
	Sun Oct  4 09:54:44 2020
$end
$version
	ModelSim Version 2020.1
$end
$timescale
	100ps
$end

$scope module d_flip_flop_TB $end
$var reg 1 ! CLK $end
$var reg 1 " D $end
$var wire 1 # Q $end
$var wire 1 $ Qbar $end
$upscope $end
$enddefinitions $end
#0
$dumpvars
0!
0"
x#
x$
$end
#500
1!
#1000
0!
0#
1$
#1250
1"
#1500
1!
#2000
0!
0$
1#
#2500
1!
#2750
0"
#3000
0!
0#
1$
#3500
1!
#4000
0!
#4250
1"
#4500
1!
#5000
0!
0$
1#
